[
  {
    "key": "kind",
    "type": "string",
    "value": "character"
  },
  {
    "key": "data",
    "type": "obj",
    "obj": [
      {
        "key": "name",
        "type": "string",
        "value": "{{D3}}"
      },
      {
        "key": "initiative",
        "type": "number",
        "value": "{{Y95}}"
      },
      {
        "key": "memo",
        "type": "string",
        "value": "{{B85}}\n{{B86}}\n{{B87}}\n{{B88}}\n{{B89}}\n{{B90}}\n{{B91}}\n{{B92}}\n{{B93}}\n{{B94}}\n{{B95}}\n{{B96}}\n{{B97}}"
      },
      {
        "key": "status",
        "type": "objArray",
        "array": [
          [
            {
              "key": "label",
              "type": "string",
              "value": "HP"
            },
            {
              "key": "value",
              "type": "number",
              "value": "{{E11}}"
            },
            {
              "key": "max",
              "type": "number",
              "value": "{{E11}}"
            }
          ],
          [
            {
              "key": "label",
              "type": "string",
              "value": "MP"
            },
            {
              "key": "value",
              "type": "number",
              "value": "{{P11}}"
            },
            {
              "key": "max",
              "type": "number",
              "value": "{{P11}}"
            }
          ],
          [
            {
              "key": "label",
              "type": "string",
              "value": "SAN"
            },
            {
              "key": "value",
              "type": "number",
              "value": "{{AF11}}"
            },
            {
              "key": "max",
              "type": "number",
              "value": "{{AF11}}"
            }
          ],
          [
            {
              "key": "label",
              "type": "string",
              "value": "LUK"
            },
            {
              "key": "value",
              "type": "number",
              "value": "{{X11}}"
            },
            {
              "key": "max",
              "type": "number",
              "value": "{{X11}}"
            }
          ]
        ]
      },
      {
        "key": "params",
        "type": "objArray",
        "array": [
          [
            {
              "key": "label",
              "type": "string",
              "value": "STR"
            },
            {
              "key": "value",
              "type": "number",
              "value": "{{S3}}"
            }
          ],
          [
            {
              "key": "label",
              "type": "string",
              "value": "CON"
            },
            {
              "key": "value",
              "type": "number",
              "value": "{{S5}}"
            }
          ],
          [
            {
              "key": "label",
              "type": "string",
              "value": "DEX"
            },
            {
              "key": "value",
              "type": "number",
              "value": "{{Y3}}"
            }
          ],
          [
            {
              "key": "label",
              "type": "string",
              "value": "APP"
            },
            {
              "key": "value",
              "type": "number",
              "value": "{{Y5}}"
            }
          ],
          [
            {
              "key": "label",
              "type": "string",
              "value": "POW"
            },
            {
              "key": "value",
              "type": "number",
              "value": "{{AE3}}"
            }
          ],
          [
            {
              "key": "label",
              "type": "string",
              "value": "SIZ"
            },
            {
              "key": "value",
              "type": "number",
              "value": "{{S7}}"
            }
          ],
          [
            {
              "key": "label",
              "type": "string",
              "value": "INT"
            },
            {
              "key": "value",
              "type": "number",
              "value": "{{Y7}}"
            }
          ],
          [
            {
              "key": "label",
              "type": "string",
              "value": "EDU"
            },
            {
              "key": "value",
              "type": "number",
              "value": "{{AE5}}"
            }
          ],
          [
            {
              "key": "label",
              "type": "string",
              "value": "MOV"
            },
            {
              "key": "value",
              "type": "number",
              "value": "{{AE7}}"
            }
          ],
          [
            {
              "key": "label",
              "type": "string",
              "value": "DB"
            },
            {
              "key": "value",
              "type": "number",
              "value": "{{A61}}"
            }
          ]
        ]
      },
      {
        "key": "commands",
        "type": "string",
        "value": "CC<={SAN} SAN\nCC<={LUK} LUK\nCC<={STR} STR\nCC<={CON} CON\nCC<={DEX} DEX\nCC<={APP} APP\nCC<={POW} POW\nCC<={SIZ} SIZ\nCC<={INT} INT\nCC<={EDU} EDU\n===調查===\nCC<={{AJ35}} 偵查\nCC<={{AJ34}} 聆聽\nCC<={{AJ36}} 圖書館使用\n===社交===\nCC<={{P35}} 心理學\nCC<={{P30}} 信用評級\nCC<={{P34}} 話術\nCC<={{P31}} 魅惑\nCC<={{P33}} 說服\nCC<={{P32}} 威嚇\nCC<={{AJ30}} 母語: {{AA30}}\n===戰鬥===\nCC<={{P36}} 閃避\nCC<={{P50}} 鬥毆\nIfNEq<<0,{{P51}},CC<={{P51}} 戰鬥: 劍\n,>>IfNEq<<0,{{P52}},CC<={{P52}} 戰鬥: {{G52}}\n,>>IfNEq<<20,{{P53}},CC<={{P53}} 火器: 手槍\n,>>IfNEq<<25,{{P54}},CC<={{P54}} 火器: 步槍or霰彈槍\n,>>IfNEq<<0,{{P55}},CC<={{P55}} 火器: {{G55}}\n,>>CC<={{P56}} 急救\n===其它===\nIfNEq<<{{AB37}},{{AJ37}},CC<={{AJ37}} 會計\n,>>IfNEq<<{{AB45}},{{AJ45}},CC<={{AJ45}} 人類學\n,>>IfNEq<<{{AB44}},{{AJ44}},CC<={{AJ44}} 估價\n,>>IfNEq<<{{AB46}},{{AJ46}},CC<={{AJ46}} 考古學\n,>>IfNEq<<{{AB51}},{{AJ51}},CC<={{AJ51}} 藝術: {{AA51}}\n,>>IfNEq<<{{AB52}},{{AJ52}},CC<={{AJ52}} 藝術: {{AA52}}\n,>>IfNEq<<{{H37}},{{P37}},CC<={{P37}} 攀爬\n,>>IfNEq<<{{AB38}},{{AJ38}},CC<={{AJ38}} 電腦使用\n,>>IfNEq<<{{AB55}},{{AJ55}},CC<={{AJ55}} 克蘇魯神話\n,>>IfNEq<<{{H46}},{{P46}},CC<={{P46}} 喬裝\n,>>IfNEq<<{{H42}},{{P42}},CC<={{P42}} 自動車駕駛\n,>>IfNEq<<{{AB39}},{{AJ39}},CC<={{AJ39}} 電器維修\n,>>IfNEq<<{{AB40}},{{AJ40}},CC<={{AJ40}} 電子學\n,>>IfNEq<<{{AB47}},{{AJ47}},CC<={{AJ47}} 歷史\n,>>IfNEq<<{{H38}},{{P38}},CC<={{P38}} 跳躍\n,>>IfNEq<<{{AB31}},{{AJ31}},CC<={{AJ31}} 他國語言: {{AA31}}\n,>>IfNEq<<{{AB32}},{{AJ32}},CC<={{AJ32}} 他國語言: {{AA32}}\n,>>IfNEq<<{{AB33}},{{AJ33}},CC<={{AJ33}} 他國語言: {{AA33}}\n,>>IfNEq<<{{AB41}},{{AJ41}},CC<={{AJ41}} 法律\n,>>IfNEq<<{{H47}},{{P47}},CC<={{P47}} 鎖匠\n,>>IfNEq<<{{AB42}},{{AJ42}},CC<={{AJ42}} 機械維修\n,>>IfNEq<<{{H57}},{{P57}},CC<={{P57}} 醫學\n,>>IfNEq<<{{AB48}},{{AJ48}},CC<={{AJ48}} 自然學\n,>>IfNEq<<{{H40}},{{P40}},CC<={{P40}} 導航\n,>>IfNEq<<{{AB49}},{{AJ49}},CC<={{AJ49}} 神秘學\n,>>IfNEq<<{{AB43}},{{AJ43}},CC<={{AJ43}} 操縱重型機械\n,>>IfNEq<<{{H43}},{{P43}},CC<={{P43}} 專業駕駛: {{G43}}\n,>>IfNEq<<{{H58}},{{P58}},CC<={{P58}} 精神分析\n,>>IfNEq<<{{H41}},{{P41}},CC<={{P41}} 騎術\n,>>IfNEq<<{{AB53}},{{AJ53}},CC<={{AJ53}} 科學: {{AA53}}\n,>>IfNEq<<{{AB54}},{{AJ54}},CC<={{AJ54}} 科學: {{AA54}}\n,>>IfNEq<<{{H48}},{{P48}},CC<={{P48}} 巧手\n,>>IfNEq<<{{H44}},{{P44}},CC<={{P44}} 隱密行動\n,>>IfNEq<<{{AB50}},{{AJ50}},CC<={{AJ50}} 生存\n,>>IfNEq<<{{H39}},{{P39}},CC<={{P39}} 游泳\n,>>IfNEq<<{{H49}},{{P49}},CC<={{P49}} 投擲\n,>>IfNEq<<{{H45}},{{P45}},CC<={{P45}} 追蹤\n,>>IfNEq<<0,{{AJ56}},CC<={{AJ56}} 罕見: {{AA56}}\n,>>IfNEq<<0,{{AJ57}},CC<={{AJ57}} 超能力: {{AA57}}\n,>>"
      }
    ]
  }
]
